Metadata-Version: 2.1
Name: odoo14-addon-sale_report_delivered_brand
Version: 14.0.1.0.1.dev6
Summary: Sale Report Delivered Brand
Home-page: https://github.com/OCA/sale-reporting
Author: Tecnativa, Odoo Community Association (OCA)
Author-email: support@odoo-community.org
License: AGPL-3
Classifier: Programming Language :: Python
Classifier: Framework :: Odoo
Classifier: Framework :: Odoo :: 14.0
Classifier: License :: OSI Approved :: GNU Affero General Public License v3
Requires-Python: >=3.6
Requires-Dist: odoo14-addon-product-brand
Requires-Dist: odoo14-addon-sale-report-delivered
Requires-Dist: odoo<14.1dev,>=14.0a
